Metadata-Version: 2.1
Name: micro-wifi-manager
Version: 0.0.4
Summary: A MicroPython WiFi manager for ESPx devices with fallback web configuration portal
Home-page: https://github.com/graham768/MicroWiFiManager
License: MIT
Platform: UNKNOWN
License-File: LICENSE
